pyexcelerate/Alignment.py
pyexcelerate/Border.py
pyexcelerate/Borders.py
pyexcelerate/Color.py
pyexcelerate/DataTypes.py
pyexcelerate/Fill.py
pyexcelerate/Font.py
pyexcelerate/Format.py
pyexcelerate/Panes.py
pyexcelerate/Range.py
pyexcelerate/Style.py
pyexcelerate/Utility.py
pyexcelerate/Workbook.py
pyexcelerate/Worksheet.py
pyexcelerate/Writer.py
pyexcelerate/__init__.py
pyexcelerate/version.py
pyexcelerate/templates/[Content_Types].xml
pyexcelerate/templates/_rels/.rels
pyexcelerate/templates/docProps/app.xml
pyexcelerate/templates/docProps/core.xml
pyexcelerate/templates/xl/styles.empty.xml
pyexcelerate/templates/xl/styles.xml
pyexcelerate/templates/xl/workbook.xml
pyexcelerate/templates/xl/_rels/workbook.xml.rels
pyexcelerate/templates/xl/worksheets/sheet.xml
pyexcelerate-0.13.0.dist-info/licenses/LICENSE
pyexcelerate-0.13.0.dist-info/METADATA
pyexcelerate-0.13.0.dist-info/WHEEL
pyexcelerate-0.13.0.dist-info/top_level.txt
pyexcelerate-0.13.0.dist-info/RECORD
