Metadata-Version: 2.4
Name: PyExcelerate
Version: 0.13.0
Summary: Accelerated Excel XLSX Writing Library for Python 2/3
Home-page: https://github.com/kz26/PyExcelerate
Author: Kevin Wang, Kevin Zhang
Author-email: kevin+pyexcelerate@kevinzhang.me
Maintainer: Kevin Zhang
Maintainer-email: kevin+pyexcelerate@kevinzhang.me
Classifier: Development Status :: 4 - Beta
Classifier: Intended Audience :: Developers
Classifier: License :: OSI Approved :: BSD License
Classifier: Programming Language :: Python :: 2.7
Classifier: Programming Language :: Python :: 3.4
Classifier: Programming Language :: Python :: 3.5
Classifier: Programming Language :: Python :: 3.6
Classifier: Programming Language :: Python :: 3.7
Classifier: Programming Language :: Python :: 3.8
License-File: LICENSE
Requires-Dist: Jinja2
Requires-Dist: six>=1.4.0
Dynamic: author
Dynamic: author-email
Dynamic: classifier
Dynamic: description
Dynamic: home-page
Dynamic: license-file
Dynamic: maintainer
Dynamic: maintainer-email
Dynamic: requires-dist
Dynamic: summary
